info/gianlucacosta/cervantes/__init__.py
info/gianlucacosta/cervantes/inspectors.py
info/gianlucacosta/cervantes/partial_term.py
info/gianlucacosta/cervantes/py.typed
info/gianlucacosta/cervantes/sqlite/__init__.py
info/gianlucacosta/cervantes/sqlite/dictionary.py
info/gianlucacosta/cervantes/sqlite/schema.py
info/gianlucacosta/cervantes/sqlite/serializers.py
info/gianlucacosta/cervantes/terms.py
info.gianlucacosta.cervantes-1.1.0.dist-info/LICENSE
info.gianlucacosta.cervantes-1.1.0.dist-info/WHEEL
info.gianlucacosta.cervantes-1.1.0.dist-info/METADATA
info.gianlucacosta.cervantes-1.1.0.dist-info/RECORD
