Metadata-Version: 2.1
Name: info.gianlucacosta.cervantes
Version: 1.1.0
Summary: Extract a compact Spanish dictionary from Wikcionario, with elegance
Home-page: https://github.com/giancosta86/Cervantes
License: MIT
Keywords: library,extract,wiki,pages,dictionary,Wiktionary,Wikcionario,Spanish
Author: Gianluca Costa
Author-email: gianluca@gianlucacosta.info
Requires-Python: >=3.10,<4.0
Classifier: Development Status :: 5 - Production/Stable
Classifier: Intended Audience :: Developers
Classifier: License :: OSI Approved :: MIT License
Classifier: Natural Language :: Spanish
Classifier: Operating System :: OS Independent
Classifier: Programming Language :: Python
Classifier: Programming Language :: Python :: 3
Classifier: Programming Language :: Python :: 3.10
Classifier: Topic :: Text Processing :: Linguistic
Requires-Dist: info.gianlucacosta.wikiprism (>=1.0.0,<2.0.0)
Project-URL: Documentation, https://github.com/giancosta86/Cervantes
Project-URL: Repository, https://github.com/giancosta86/Cervantes
